sincpro_async_worker/__init__.py
sincpro_async_worker/core.py
sincpro_async_worker/domain/__init__.py
sincpro_async_worker/domain/dispatcher.py
sincpro_async_worker/domain/worker.py
sincpro_async_worker/exceptions.py
sincpro_async_worker/infrastructure/__init__.py
sincpro_async_worker/infrastructure/dispatcher.py
sincpro_async_worker/infrastructure/event_loop.py
sincpro_async_worker/infrastructure/worker.py
sincpro_async_worker-0.3.0.dist-info/LICENSE.md
sincpro_async_worker-0.3.0.dist-info/METADATA
sincpro_async_worker-0.3.0.dist-info/WHEEL
sincpro_async_worker-0.3.0.dist-info/RECORD
