Metadata-Version: 2.3
Name: sincpro-async-worker
Version: 0.3.0
Summary: Componente asíncrono para sincpro_framework que permite ejecutar tareas asíncronas en un entorno mayoritariamente sincrónico
License: SINCPRO S.R.L.
Author: Gutierrez, Andres
Author-email: andru1236@gmail.com
Requires-Python: >=3.12,<4.0
Classifier: License :: Other/Proprietary License
Classifier: Programming Language :: Python :: 3
Classifier: Programming Language :: Python :: 3.12
Classifier: Programming Language :: Python :: 3.13
